rtl/uart_tx.v
module uart_tx #(
    parameter CLKS_PER_BIT = 16
)(
    input        clk,
    input        reset,
    input        start,
    input  [7:0] data,
    output reg   tx,
    output reg   busy
);

    localparam IDLE  = 2'b00;
    localparam START = 2'b01;
    localparam DATA  = 2'b10;
    localparam STOP  = 2'b11;

    reg [1:0]  state;
    reg [7:0]  data_reg;
    reg [3:0]  bit_index;
    reg [15:0] baud_count;

    always @(posedge clk or posedge reset) begin
        if (reset) begin
            state      <= IDLE;
            data_reg   <= 8'b0;
            bit_index  <= 4'b0;
            baud_count <= 16'b0;
            tx         <= 1'b1;
            busy       <= 1'b0;
        end
        else begin
            case (state)

                IDLE: begin
                    tx         <= 1'b1;
                    busy       <= 1'b0;
                    baud_count <= 16'b0;
                    bit_index  <= 4'b0;

                    if (start) begin
                        data_reg <= data;
                        busy     <= 1'b1;
                        state    <= START;
                    end
                end

                START: begin
                    tx   <= 1'b0;
                    busy <= 1'b1;

                    if (baud_count == CLKS_PER_BIT-1) begin
                        baud_count <= 16'b0;
                        state      <= DATA;
                    end
                    else begin
                        baud_count <= baud_count + 1'b1;
                    end
                end

                DATA: begin
                    tx   <= data_reg[bit_index];
                    busy <= 1'b1;

                    if (baud_count == CLKS_PER_BIT-1) begin
                        baud_count <= 16'b0;

                        if (bit_index == 4'd7) begin
                            bit_index <= 4'b0;
                            state     <= STOP;
                        end
                        else begin
                            bit_index <= bit_index + 1'b1;
                        end
                    end
                    else begin
                        baud_count <= baud_count + 1'b1;
                    end
                end

                STOP: begin
                    tx   <= 1'b1;
                    busy <= 1'b1;

                    if (baud_count == CLKS_PER_BIT-1) begin
                        baud_count <= 16'b0;
                        state      <= IDLE;
                        busy       <= 1'b0;
                    end
                    else begin
                        baud_count <= baud_count + 1'b1;
                    end
                end

                default: begin
                    state <= IDLE;
                    tx    <= 1'b1;
                    busy  <= 1'b0;
                end

            endcase
        end
    end

endmodule

simulation/tb_uart_tx.v
`timescale 1ns/1ps

module tb_uart_tx;

reg clk;
reg reset;
reg start;
reg [7:0] data;

wire tx;
wire busy;

uart_tx #(
    .CLKS_PER_BIT(4)
) uut (
    .clk(clk),
    .reset(reset),
    .start(start),
    .data(data),
    .tx(tx),
    .busy(busy)
);

always #5 clk = ~clk;

initial begin

    $dumpfile("simulation/uart_tx.vcd");
    $dumpvars(0, tb_uart_tx);

    clk = 0;
    reset = 1;
    start = 0;
    data = 8'h00;

    #20;
    reset = 0;

    // Transmit ASCII A
    #10;
    data = 8'h41;
    start = 1;

    #10;
    start = 0;

    // Wait for complete transmission
    #500;

    $display("UART transmission completed.");
    $display("Data transmitted = 0x%h", data);

    $finish;

end

endmodule

simulation/uart_tx.vcd
$date
	Wed Oct  7 21:30:11 2026
$end
$version
	Icarus Verilog
$end
$timescale
	1ps
$end
$scope module tb_uart_tx $end
$var wire 1 ! tx $end
$var wire 1 " busy $end
$var reg 1 # clk $end
$var reg 8 $ data [7:0] $end
$var reg 1 % reset $end
$var reg 1 & start $end
$scope module uut $end
$var wire 1 # clk $end
$var wire 8 ' data [7:0] $end
$var wire 1 % reset $end
$var wire 1 & start $end
$var parameter 32 ( CLKS_PER_BIT $end
$var parameter 2 ) DATA $end
$var parameter 2 * IDLE $end
$var parameter 2 + START $end
$var parameter 2 , STOP $end
$var reg 16 - baud_count [15:0] $end
$var reg 4 . bit_index [3:0] $end
$var reg 1 " busy $end
$var reg 8 / data_reg [7:0] $end
$var reg 2 0 state [1:0] $end
$var reg 1 ! tx $end
$upscope $end
$upscope $end
$enddefinitions $end
$comment Show the parameter values. $end
$dumpall
b11 ,
b1 +
b0 *
b10 )
b100 (
$end
#0
$dumpvars
b0 0
b0 /
b0 .
b0 -
b0 '
0&
1%
b0 $
0#
0"
1!
$end
#5000
1#
#10000
0#
#15000
1#
#20000
0#
0%
#25000
1#
#30000
0#
1&
b1000001 $
b1000001 '
#35000
b1 0
1"
b1000001 /
1#
#40000
0#
0&
#45000
b1 -
0!
1#
#50000
0#
#55000
b10 -
1#
#60000
0#
#65000
b11 -
1#
#70000
0#
#75000
b10 0
b0 -
1#
#80000
0#
#85000
b1 -
1!
1#
#90000
0#
#95000
b10 -
1#
#100000
0#
#105000
b11 -
1#
#110000
0#
#115000
b1 .
b0 -
1#
#120000
0#
#125000
b1 -
0!
1#
#130000
0#
#135000
b10 -
1#
#140000
0#
#145000
b11 -
1#
#150000
0#
#155000
b10 .
b0 -
1#
#160000
0#
#165000
b1 -
1#
#170000
0#
#175000
b10 -
1#
#180000
0#
#185000
b11 -
1#
#190000
0#
#195000
b11 .
b0 -
1#
#200000
0#
#205000
b1 -
1#
#210000
0#
#215000
b10 -
1#
#220000
0#
#225000
b11 -
1#
#230000
0#
#235000
b100 .
b0 -
1#
#240000
0#
#245000
b1 -
1#
#250000
0#
#255000
b10 -
1#
#260000
0#
#265000
b11 -
1#
#270000
0#
#275000
b101 .
b0 -
1#
#280000
0#
#285000
b1 -
1#
#290000
0#
#295000
b10 -
1#
#300000
0#
#305000
b11 -
1#
#310000
0#
#315000
b110 .
b0 -
1#
#320000
0#
#325000
b1 -
1!
1#
#330000
0#
#335000
b10 -
1#
#340000
0#
#345000
b11 -
1#
#350000
0#
#355000
b111 .
b0 -
1#
#360000
0#
#365000
b1 -
0!
1#
#370000
0#
#375000
b10 -
1#
#380000
0#
#385000
b11 -
1#
#390000
0#
#395000
b11 0
b0 .
b0 -
1#
#400000
0#
#405000
b1 -
1!
1#
#410000
0#
#415000
b10 -
1#
#420000
0#
#425000
b11 -
1#
#430000
0#
#435000
0"
b0 0
b0 -
1#
